qbittorrent/__init__.py
qbittorrent/client.py
python_qbittorrent-0.4.3.dist-info/LICENSE
python_qbittorrent-0.4.3.dist-info/METADATA
python_qbittorrent-0.4.3.dist-info/WHEEL
python_qbittorrent-0.4.3.dist-info/top_level.txt
python_qbittorrent-0.4.3.dist-info/RECORD
