Metadata-Version: 2.1
Name: python-qbittorrent
Version: 0.4.3
Summary: Python wrapper for qBittorrent >4.1.x
Home-page: https://github.com/v1k45/python-qbittorrent
Author: Vikas Yadav
Author-email: v1k45x@gmail.com
License: The MIT License
Keywords: torrent,qBittorent,API,wrapper
Platform: OS Independent
Classifier: Development Status :: 5 - Production/Stable
Classifier: Intended Audience :: Developers
Classifier: Operating System :: OS Independent
Classifier: Programming Language :: Python
Classifier: Programming Language :: Python :: 2.7
Classifier: Programming Language :: Python :: 3.4
Classifier: Programming Language :: Python :: 3.5
Classifier: Programming Language :: Python :: 3.6
Classifier: Programming Language :: Python :: 3.7
Classifier: Programming Language :: Python :: 3.8
Classifier: Programming Language :: Python :: 3.9
Classifier: Programming Language :: Python :: 3.10
Classifier: License :: OSI Approved :: MIT License
Classifier: Environment :: Console
License-File: LICENSE
